reflective_listening/__init__.py
reflective_listening/parametric.py
reflective_listening/reflective_listening.py
reflective_listening-0.1.3.dist-info/LICENSE
reflective_listening-0.1.3.dist-info/METADATA
reflective_listening-0.1.3.dist-info/WHEEL
reflective_listening-0.1.3.dist-info/top_level.txt
reflective_listening-0.1.3.dist-info/RECORD
