Metadata-Version: 2.1
Name: reflective-listening
Version: 0.1.3
Summary: Reflective listening statements via paraphrase generation
Home-page: http://github.com/monmanuela/reflective_listening
Author: Monika Manuela Hengki
Author-email: e0014971@u.nus.edu
License: MIT
Platform: UNKNOWN
Requires-Python: >=3.6.2
Requires-Dist: language-tool-python
Requires-Dist: nltk
Requires-Dist: numpy
Requires-Dist: sentence-transformers
Requires-Dist: scipy (==1.4.1)
Requires-Dist: sentencepiece
Requires-Dist: torch
Requires-Dist: transformers
